{"book_id_title": "114954", "book_id": "114954", "book_title": "The Opal Deception", "book_series": "Artemis Fowl #4", "book_series_uri": "/series/42742-artemis-fowl", "isbn": "0141315490", "isbn13": "9780141315492", "year_first_published": "2005", "author": "Eoin Colfer", "num_pages": 416, "genres": ["Fantasy", "Young Adult", "Fiction", "Science Fiction", "Childrens > Middle Grade", "Childrens", "Adventure", "Fantasy > Magic", "Fantasy > Urban Fantasy", "Audiobook"], "num_ratings": "140141", "num_reviews": "2185", "average_rating": "4.03", "rating_distribution": {"5 Stars": 51141, "4 Stars": 52445, "3 Stars": 28324, "2 Stars": 5645, "1 Star": 2586}}