{"book_id_title": "12820360", "book_id": "12820360", "book_title": "Edenbrooke", "book_series": "Edenbrooke #1", "book_series_uri": "/series/117949-edenbrooke", "isbn": "8415854285", "isbn13": "9788415854289", "year_first_published": "", "author": "Julianne Donaldson", "num_pages": 264, "genres": ["Romance", "Historical > Historical Fiction", "Romance > Historical Romance", "Historical", "Fiction", "Historical > Regency", "Romance > Clean Romance", "Historical Romance > Regency Romance", "Womens Fiction > Chick Lit", "Adult"], "num_ratings": "45642", "num_reviews": "9028", "average_rating": "4.32", "rating_distribution": {"5 Stars": 24053, "4 Stars": 14307, "3 Stars": 5487, "2 Stars": 1256, "1 Star": 539}}