{"book_id_title": "13596166", "book_id": "13596166", "book_title": "Joyland", "book_series": "", "book_series_uri": "", "isbn": "1781167699", "isbn13": "9781781167694", "year_first_published": "", "author": "Stephen King", "num_pages": 283, "genres": ["Horror", "Mystery", "Fiction", "Thriller", "Mystery > Crime", "Thriller > Mystery Thriller", "Fantasy > Paranormal", "Audiobook", "Suspense", "Young Adult > Coming Of Age"], "num_ratings": "139741", "num_reviews": "13293", "average_rating": "3.92", "rating_distribution": {"5 Stars": 42288, "4 Stars": 56862, "3 Stars": 30651, "2 Stars": 7210, "1 Star": 2730}}