{"book_id_title": "13605727", "book_id": "13605727", "book_title": "Elixir", "book_series": "Covenant #3.5", "book_series_uri": "/series/53954-covenant", "isbn": "1937053407", "isbn13": "9781937053406", "year_first_published": "2012", "author": "Jennifer L. Armentrout", "num_pages": 74, "genres": ["Young Adult", "Fantasy", "Fantasy > Paranormal", "Fantasy > Mythology", "Romance", "Romance > Paranormal Romance", "Novella", "Mythology > Greek Mythology", "Fantasy > Urban Fantasy", "Fantasy > Supernatural"], "num_ratings": "30719", "num_reviews": "2032", "average_rating": "4.37", "rating_distribution": {"5 Stars": 16795, "4 Stars": 9391, "3 Stars": 3704, "2 Stars": 651, "1 Star": 178}}