{"book_id_title": "14569052", "book_id": "14569052", "book_title": "Purple Hibiscus", "book_series": "", "book_series_uri": "", "isbn": "isbn not found", "isbn13": "isbn13 not found", "year_first_published": "2003", "author": "Chimamanda Ngozi Adichie", "num_pages": 336, "genres": ["Fiction", "Cultural > Africa", "Historical > Historical Fiction", "Western Africa > Nigeria", "Contemporary", "Literary Fiction", "Literature > African Literature", "Novels", "Young Adult", "Young Adult > Coming Of Age"], "num_ratings": "93318", "num_reviews": "7756", "average_rating": "4.17", "rating_distribution": {"5 Stars": 36656, "4 Stars": 40111, "3 Stars": 13156, "2 Stars": 2401, "1 Star": 994}}