{"book_id_title": "17997353", "book_id": "17997353", "book_title": "The Tailor", "book_series": "The Shadow and Bone Trilogy #1.5", "book_series_uri": "/series/69714-the-shadow-and-bone-trilogy", "isbn": "isbn not found", "isbn13": "isbn13 not found", "year_first_published": "", "author": "Leigh Bardugo", "num_pages": 18, "genres": ["Fantasy", "Young Adult", "Short Stories", "Novella", "Fiction", "Fantasy > Magic", "Fantasy > High Fantasy", "Young Adult > Young Adult Fantasy", "Fantasy > Paranormal", "Romance"], "num_ratings": "21202", "num_reviews": "2473", "average_rating": "3.75", "rating_distribution": {"5 Stars": 4525, "4 Stars": 8290, "3 Stars": 7082, "2 Stars": 1166, "1 Star": 139}}