{"book_id_title": "18079527", "book_id": "18079527", "book_title": "The Impossible Knife of Memory", "book_series": "", "book_series_uri": "", "isbn": "0147510724", "isbn13": "9780147510723", "year_first_published": "2014", "author": "Laurie Halse Anderson", "num_pages": 391, "genres": ["Young Adult", "Contemporary", "Realistic Fiction", "Fiction", "Romance", "Health > Mental Health", "Mental Health > Mental Illness", "War", "Young Adult > Teen", "Family"], "num_ratings": "27774", "num_reviews": "3759", "average_rating": "3.91", "rating_distribution": {"5 Stars": 8639, "4 Stars": 10784, "3 Stars": 6246, "2 Stars": 1524, "1 Star": 581}}