{"book_id_title": "193755", "book_id": "193755", "book_title": "The Diving Bell and the Butterfly", "book_series": "", "book_series_uri": "", "isbn": "0007139845", "isbn13": "9789938833867", "year_first_published": "1997", "author": "Jean-Dominique Bauby", "num_pages": 132, "genres": ["Nonfiction", "Autobiography > Memoir", "Biography", "Biography Memoir", "Biography > Autobiography", "Cultural > France", "Health > Medicine", "Medical", "Classics", "Disability"], "num_ratings": "68556", "num_reviews": "4888", "average_rating": "3.96", "rating_distribution": {"5 Stars": 23612, "4 Stars": 25563, "3 Stars": 13971, "2 Stars": 3801, "1 Star": 1609}}