{"book_id_title": "2020935", "book_id": "2020935", "book_title": "Sweethearts", "book_series": "", "book_series_uri": "", "isbn": "0316014567", "isbn13": "9780316014564", "year_first_published": "", "author": "Sara Zarr", "num_pages": 217, "genres": ["Young Adult", "Contemporary", "Romance", "Fiction", "Realistic Fiction", "Young Adult > Teen", "Sociology > Abuse", "Young Adult > High School", "Young Adult > Young Adult Contemporary", "Womens Fiction > Chick Lit"], "num_ratings": "18096", "num_reviews": "1770", "average_rating": "3.63", "rating_distribution": {"5 Stars": 4605, "4 Stars": 5427, "3 Stars": 5420, "2 Stars": 1997, "1 Star": 647}}