{"book_id_title": "23657454", "book_id": "23657454", "book_title": "Awkward", "book_series": "Berrybrook Middle School #1", "book_series_uri": "/series/250869-berrybrook-middle-school", "isbn": "0316381322", "isbn13": "9780316381321", "year_first_published": "", "author": "Svetlana Chmakova", "num_pages": 224, "genres": ["Sequential Art > Graphic Novels", "Childrens > Middle Grade", "Realistic Fiction", "Sequential Art > Comics", "Young Adult", "Fiction", "Contemporary", "Childrens", "Childrens > Juvenile", "Art"], "num_ratings": "41112", "num_reviews": "2256", "average_rating": "4.16", "rating_distribution": {"5 Stars": 20949, "4 Stars": 10948, "3 Stars": 5788, "2 Stars": 1878, "1 Star": 1549}}