{"book_id_title": "25753113", "book_id": "25753113", "book_title": "Genesis Begins Again", "book_series": "", "book_series_uri": "", "isbn": "1481465805", "isbn13": "9781481465809", "year_first_published": "", "author": "Alicia D. Williams", "num_pages": 400, "genres": ["Childrens > Middle Grade", "Realistic Fiction", "Young Adult", "Fiction", "Contemporary", "Cultural > African American", "Family", "Audiobook", "Race", "Childrens"], "num_ratings": "6578", "num_reviews": "1143", "average_rating": "4.38", "rating_distribution": {"5 Stars": 3304, "4 Stars": 2594, "3 Stars": 599, "2 Stars": 60, "1 Star": 21}}