{"book_id_title": "26148083", "book_id": "26148083", "book_title": "Rhythm, Chord & Malykhin", "book_series": "", "book_series_uri": "", "isbn": "0990429229", "isbn13": "9788025347140", "year_first_published": "", "author": "Mariana Zapata", "num_pages": 398, "genres": ["Romance", "Contemporary", "Romance > Contemporary Romance", "New Adult", "Music", "Humor", "Audiobook", "Adult", "Music > Musicians", "Fiction"], "num_ratings": "22864", "num_reviews": "2066", "average_rating": "4.00", "rating_distribution": {"5 Stars": 8023, "4 Stars": 8692, "3 Stars": 4708, "2 Stars": 1073, "1 Star": 368}}