{"book_id_title": "29864343", "book_id": "29864343", "book_title": "Rich People Problems", "book_series": "Crazy Rich Asians #3", "book_series_uri": "/series/138257-crazy-rich-asians", "isbn": "0385689403", "isbn13": "9780525432371", "year_first_published": "", "author": "Kevin Kwan", "num_pages": 398, "genres": ["Fiction", "Contemporary", "Romance", "Womens Fiction > Chick Lit", "Audiobook", "Adult", "Humor", "Cultural > Asia", "Adult Fiction", "Literature > Asian Literature"], "num_ratings": "146291", "num_reviews": "9570", "average_rating": "3.93", "rating_distribution": {"5 Stars": 41692, "4 Stars": 62261, "3 Stars": 34717, "2 Stars": 5782, "1 Star": 1839}}