{"book_id_title": "30269104", "book_id": "30269104", "book_title": "The Chilbury Ladies' Choir", "book_series": "", "book_series_uri": "", "isbn": "1101906774", "isbn13": "9781101906774", "year_first_published": "", "author": "Jennifer Ryan", "num_pages": 371, "genres": ["Historical > Historical Fiction", "Fiction", "War > World War II", "Historical", "European Literature > British Literature", "War", "Audiobook", "Adult", "Adult Fiction", "Romance"], "num_ratings": "30554", "num_reviews": "4688", "average_rating": "3.96", "rating_distribution": {"5 Stars": 8688, "4 Stars": 14129, "3 Stars": 5964, "2 Stars": 1255, "1 Star": 518}}