{"book_id_title": "30631124", "book_id": "30631124", "book_title": "Pretty Face", "book_series": "London Celebrities #2", "book_series_uri": "/series/198158-london-celebrities", "isbn": "1335013261", "isbn13": "9781335013262", "year_first_published": "", "author": "Lucy Parker", "num_pages": 372, "genres": ["Romance", "Contemporary", "Romance > Contemporary Romance", "Adult", "Fiction", "Audiobook", "Womens Fiction > Chick Lit", "Humor", "Adult Fiction", "European Literature > British Literature"], "num_ratings": "4999", "num_reviews": "846", "average_rating": "4.05", "rating_distribution": {"5 Stars": 1667, "4 Stars": 2163, "3 Stars": 973, "2 Stars": 153, "1 Star": 43}}