{"book_id_title": "31307650", "book_id": "31307650", "book_title": "The Day of the Duchess", "book_series": "Scandal & Scoundrel #3", "book_series_uri": "/series/141485-scandal-scoundrel", "isbn": "0062379437", "isbn13": "9780062379436", "year_first_published": "", "author": "Sarah MacLean", "num_pages": 400, "genres": ["Romance", "Romance > Historical Romance", "Historical", "Historical > Historical Fiction", "Fiction", "Historical > Regency", "Adult", "Historical Romance > Regency Romance", "Audiobook", "Adult Fiction"], "num_ratings": "12517", "num_reviews": "1741", "average_rating": "3.92", "rating_distribution": {"5 Stars": 4065, "4 Stars": 4661, "3 Stars": 2799, "2 Stars": 762, "1 Star": 230}}