{"book_id_title": "3263607", "book_id": "3263607", "book_title": "The Fellowship of the Ring", "book_series": "The Lord of the Rings #1", "book_series_uri": "/series/66175-the-lord-of-the-rings", "isbn": "0618346252", "isbn13": "9780618346257", "year_first_published": "1954", "author": "J.R.R. Tolkien", "num_pages": 527, "genres": ["Fantasy", "Fiction", "Classics", "Adventure", "Science Fiction Fantasy", "Fantasy > High Fantasy", "Fantasy > Epic Fantasy", "Young Adult", "Audiobook", "Novels"], "num_ratings": "2541669", "num_reviews": "27749", "average_rating": "4.37", "rating_distribution": {"5 Stars": 1501512, "4 Stars": 658417, "3 Stars": 259678, "2 Stars": 71519, "1 Star": 50543}}