{"book_id_title": "33230173", "book_id": "33230173", "book_title": "The Summer Palace", "book_series": "Captive Prince Short Stories #2", "book_series_uri": "/series/187877-captive-prince-short-stories", "isbn": "isbn not found", "isbn13": "9789863619390", "year_first_published": "", "author": "C.S. Pacat", "num_pages": 30, "genres": ["Fantasy", "Romance", "LGBT", "Romance > M M Romance", "Short Stories", "Adult", "Historical", "Fiction", "Novella", "LGBT > Queer"], "num_ratings": "11802", "num_reviews": "1524", "average_rating": "4.43", "rating_distribution": {"5 Stars": 7007, "4 Stars": 3281, "3 Stars": 1214, "2 Stars": 215, "1 Star": 85}}