{"book_id_title": "35068618", "book_id": "35068618", "book_title": "On the Come Up", "book_series": "", "book_series_uri": "", "isbn": "0062498568", "isbn13": "9780062498564", "year_first_published": "", "author": "Angie Thomas", "num_pages": 464, "genres": ["Young Adult", "Contemporary", "Fiction", "Audiobook", "Realistic Fiction", "Music", "Young Adult > Young Adult Contemporary", "Race", "Young Adult > Teen", "Family"], "num_ratings": "81505", "num_reviews": "11136", "average_rating": "4.30", "rating_distribution": {"5 Stars": 36553, "4 Stars": 34359, "3 Stars": 9119, "2 Stars": 1130, "1 Star": 344}}