{"book_id_title": "36586697", "book_id": "36586697", "book_title": "Queenie", "book_series": "", "book_series_uri": "", "isbn": "1501196014", "isbn13": "9781501196010", "year_first_published": "", "author": "Candice Carty-Williams", "num_pages": 330, "genres": ["Fiction", "Contemporary", "Audiobook", "Adult", "Health > Mental Health", "Feminism", "Race", "Adult Fiction", "Literary Fiction", "Womens Fiction > Chick Lit"], "num_ratings": "109452", "num_reviews": "10940", "average_rating": "3.88", "rating_distribution": {"5 Stars": 29078, "4 Stars": 46843, "3 Stars": 26244, "2 Stars": 5810, "1 Star": 1477}}