{"book_id_title": "37743", "book_id": "37743", "book_title": "Forever . . .", "book_series": "", "book_series_uri": "", "isbn": "1416934006", "isbn13": "9781416934004", "year_first_published": "1975", "author": "Judy Blume", "num_pages": 178, "genres": ["Young Adult", "Romance", "Fiction", "Contemporary", "Young Adult > Teen", "Classics", "Womens Fiction > Chick Lit", "Young Adult > Coming Of Age", "Realistic Fiction", "Literature > Banned Books"], "num_ratings": "59382", "num_reviews": "4099", "average_rating": "3.62", "rating_distribution": {"5 Stars": 15169, "4 Stars": 18446, "3 Stars": 16712, "2 Stars": 6378, "1 Star": 2677}}