{"book_id_title": "38355410", "book_id": "38355410", "book_title": "Elevation", "book_series": "", "book_series_uri": "", "isbn": "1473691524", "isbn13": "9781473691520", "year_first_published": "", "author": "Stephen King", "num_pages": 146, "genres": ["Fiction", "Horror", "Fantasy", "Audiobook", "Short Stories", "Novella", "Mystery", "Science Fiction", "Adult", "Thriller"], "num_ratings": "98261", "num_reviews": "12070", "average_rating": "3.67", "rating_distribution": {"5 Stars": 22367, "4 Stars": 34998, "3 Stars": 29647, "2 Stars": 8609, "1 Star": 2640}}