{"book_id_title": "39216077", "book_id": "39216077", "book_title": "Ember Queen", "book_series": "Ash Princess Trilogy #3", "book_series_uri": "/series/191507-ash-princess-trilogy", "isbn": "8418318449", "isbn13": "9781524767143", "year_first_published": "", "author": "Laura Sebastian", "num_pages": 512, "genres": ["Fantasy", "Young Adult", "Romance", "Young Adult > Young Adult Fantasy", "Fiction", "Fantasy > Magic", "Fantasy > High Fantasy", "Audiobook", "Science Fiction > Dystopia", "Romance > Fantasy Romance"], "num_ratings": "15465", "num_reviews": "1507", "average_rating": "4.06", "rating_distribution": {"5 Stars": 5519, "4 Stars": 6262, "3 Stars": 2948, "2 Stars": 592, "1 Star": 144}}