{"book_id_title": "395851", "book_id": "395851", "book_title": "The Struggle", "book_series": "The Vampire Diaries #2", "book_series_uri": "/series/42314-the-vampire-diaries", "isbn": "8408082191", "isbn13": "9788408082194", "year_first_published": "1991", "author": "L.J. Smith", "num_pages": 278, "genres": ["Young Adult", "Paranormal > Vampires", "Fantasy", "Romance", "Fantasy > Paranormal", "Fiction", "Romance > Paranormal Romance", "Fantasy > Supernatural", "Fantasy > Urban Fantasy", "Horror"], "num_ratings": "37351", "num_reviews": "1466", "average_rating": "3.46", "rating_distribution": {"5 Stars": 8208, "4 Stars": 9842, "3 Stars": 12068, "2 Stars": 5403, "1 Star": 1830}}