{"book_id_title": "39816076", "book_id": "39816076", "book_title": "The Lost Girls of Paris", "book_series": "", "book_series_uri": "", "isbn": "0778308618", "isbn13": "9780778308614", "year_first_published": "", "author": "Pam Jenoff", "num_pages": 377, "genres": ["Historical > Historical Fiction", "Fiction", "Historical", "War > World War II", "Audiobook", "War", "Adult", "Cultural > France", "Mystery", "Adult Fiction"], "num_ratings": "81608", "num_reviews": "7914", "average_rating": "3.89", "rating_distribution": {"5 Stars": 21078, "4 Stars": 36448, "3 Stars": 18910, "2 Stars": 4106, "1 Star": 1066}}