{"book_id_title": "40648401", "book_id": "40648401", "book_title": "Normal People", "book_series": "", "book_series_uri": "", "isbn": "1984822179", "isbn13": "9781984822178", "year_first_published": "", "author": "Sally Rooney", "num_pages": 268, "genres": ["Fiction", "Contemporary", "Romance", "Literary Fiction", "Audiobook", "Cultural > Ireland", "Adult", "Novels", "Adult Fiction", "European Literature > Irish Literature"], "num_ratings": "717769", "num_reviews": "64569", "average_rating": "3.85", "rating_distribution": {"5 Stars": 222831, "4 Stars": 258780, "3 Stars": 162995, "2 Stars": 55104, "1 Star": 18059}}