{"book_id_title": "43568394", "book_id": "43568394", "book_title": "The Guinevere Deception", "book_series": "Camelot Rising #1", "book_series_uri": "/series/255942-camelot-rising", "isbn": "0525581707", "isbn13": "9780525581703", "year_first_published": "", "author": "Kiersten White", "num_pages": 352, "genres": ["Fantasy", "Young Adult", "Retellings", "Young Adult > Young Adult Fantasy", "Historical > Historical Fiction", "Romance", "Fantasy > Magic", "Fiction", "Fantasy > Mythology", "Historical"], "num_ratings": "15588", "num_reviews": "3541", "average_rating": "3.79", "rating_distribution": {"5 Stars": 3679, "4 Stars": 6457, "3 Stars": 4113, "2 Stars": 1120, "1 Star": 219}}