{"book_id_title": "49494954", "book_id": "49494954", "book_title": "The Enigma Game", "book_series": "Code Name Verity #2", "book_series_uri": "/series/94411-code-name-verity", "isbn": "1368012582", "isbn13": "9781368012584", "year_first_published": "", "author": "Elizabeth Wein", "num_pages": 320, "genres": ["Historical > Historical Fiction", "Young Adult", "Historical", "Fiction", "War > World War II", "War", "Adventure", "Mystery", "Young Adult > Teen", "Young Adult > Young Adult Historical Fiction"], "num_ratings": "2208", "num_reviews": "454", "average_rating": "3.97", "rating_distribution": {"5 Stars": 607, "4 Stars": 1017, "3 Stars": 504, "2 Stars": 65, "1 Star": 15}}