{"book_id_title": "50496918", "book_id": "50496918", "book_title": "Spoiler Alert", "book_series": "Spoiler Alert #1", "book_series_uri": "/series/301264-spoiler-alert", "isbn": "0349427976", "isbn13": "9780349427973", "year_first_published": "", "author": "Olivia Dade", "num_pages": 416, "genres": ["Romance", "Contemporary", "Fiction", "Romance > Contemporary Romance", "Adult", "Womens Fiction > Chick Lit", "Audiobook", "Adult Fiction", "Young Adult", "New Adult"], "num_ratings": "24360", "num_reviews": "5387", "average_rating": "3.76", "rating_distribution": {"5 Stars": 5999, "4 Stars": 9518, "3 Stars": 6343, "2 Stars": 1903, "1 Star": 597}}