{"book_id_title": "5166", "book_id": "5166", "book_title": "Midwives", "book_series": "", "book_series_uri": "", "isbn": "0517703963", "isbn13": "9780517703960", "year_first_published": "1997", "author": "Chris Bohjalian", "num_pages": 384, "genres": ["Fiction", "Contemporary", "Adult Fiction", "Book Club", "Adult", "Womens Fiction > Chick Lit", "Mystery", "Novels", "Historical > Historical Fiction", "Drama"], "num_ratings": "154178", "num_reviews": "4601", "average_rating": "3.99", "rating_distribution": {"5 Stars": 48187, "4 Stars": 64743, "3 Stars": 33971, "2 Stars": 5830, "1 Star": 1447}}