{"book_id_title": "52377380", "book_id": "52377380", "book_title": "Valentine", "book_series": "", "book_series_uri": "", "isbn": "0062913271", "isbn13": "9780062913272", "year_first_published": "", "author": "Elizabeth Wetmore", "num_pages": 320, "genres": ["Fiction", "Historical > Historical Fiction", "Literary Fiction", "Audiobook", "Historical", "Adult", "Mystery > Crime", "Adult Fiction", "Contemporary", "Mystery"], "num_ratings": "33916", "num_reviews": "4681", "average_rating": "3.79", "rating_distribution": {"5 Stars": 8325, "4 Stars": 13787, "3 Stars": 8819, "2 Stars": 2390, "1 Star": 595}}