{"book_id_title": "53240817", "book_id": "53240817", "book_title": "Amari and the Night Brothers", "book_series": "Supernatural Investigations #1", "book_series_uri": "/series/299769-supernatural-investigations", "isbn": "0062975161", "isbn13": "9780062975164", "year_first_published": "", "author": "B.B. Alston", "num_pages": 416, "genres": ["Fantasy", "Childrens > Middle Grade", "Mystery", "Fantasy > Magic", "Fiction", "Childrens", "Audiobook", "Adventure", "Fantasy > Paranormal", "Young Adult"], "num_ratings": "10831", "num_reviews": "2596", "average_rating": "4.48", "rating_distribution": {"5 Stars": 6324, "4 Stars": 3523, "3 Stars": 827, "2 Stars": 126, "1 Star": 31}}