{"book_id_title": "5359", "book_id": "5359", "book_title": "The Client", "book_series": "", "book_series_uri": "", "isbn": "0440213525", "isbn13": "9780440213529", "year_first_published": "1993", "author": "John Grisham", "num_pages": 483, "genres": ["Fiction", "Mystery", "Thriller", "Mystery > Crime", "Suspense", "Thriller > Legal Thriller", "Thriller > Mystery Thriller", "Drama", "Novels", "Law"], "num_ratings": "421171", "num_reviews": "2754", "average_rating": "4.03", "rating_distribution": {"5 Stars": 145803, "4 Stars": 164080, "3 Stars": 92490, "2 Stars": 14881, "1 Star": 3917}}