{"book_id_title": "55711726", "book_id": "55711726", "book_title": "The People We Keep", "book_series": "", "book_series_uri": "", "isbn": "1797124366", "isbn13": "9781797124360", "year_first_published": "", "author": "Allison Larkin", "num_pages": 368, "genres": ["Fiction", "Historical > Historical Fiction", "Contemporary", "Audiobook", "Young Adult > Coming Of Age", "Young Adult", "Music", "Adult", "Historical", "Literary Fiction"], "num_ratings": "21749", "num_reviews": "3001", "average_rating": "4.23", "rating_distribution": {"5 Stars": 9378, "4 Stars": 8846, "3 Stars": 2849, "2 Stars": 503, "1 Star": 173}}