{"book_id_title": "56783258", "book_id": "56783258", "book_title": "Cloud Cuckoo Land", "book_series": "", "book_series_uri": "", "isbn": "0008478651", "isbn13": "9780008478650", "year_first_published": "", "author": "Anthony Doerr", "num_pages": 626, "genres": ["Fiction", "Historical > Historical Fiction", "Fantasy", "Science Fiction", "Literary Fiction", "Historical", "Adult", "Audiobook", "Writing > Books About Books", "Adult Fiction"], "num_ratings": "37206", "num_reviews": "7045", "average_rating": "4.32", "rating_distribution": {"5 Stars": 20074, "4 Stars": 11276, "3 Stars": 4028, "2 Stars": 1222, "1 Star": 606}}