{"book_id_title": "71867", "book_id": "71867", "book_title": "The Other Side of Dawn", "book_series": "Tomorrow #7", "book_series_uri": "/series/40990-tomorrow", "isbn": "0330362135", "isbn13": "9780330362139", "year_first_published": "1999", "author": "John Marsden", "num_pages": 336, "genres": ["Young Adult", "Fiction", "War", "Science Fiction > Dystopia", "Cultural > Australia", "Adventure", "Action", "Science Fiction", "Young Adult > Teen", "Adventure > Survival"], "num_ratings": "14781", "num_reviews": "437", "average_rating": "4.19", "rating_distribution": {"5 Stars": 6319, "4 Stars": 5576, "3 Stars": 2364, "2 Stars": 385, "1 Star": 137}}