{"book_id_title": "744615", "book_id": "744615", "book_title": "Scott Pilgrim, Volume 4: Scott Pilgrim Gets It Together", "book_series": "Scott Pilgrim #4", "book_series_uri": "/series/40623-scott-pilgrim", "isbn": "1620100037", "isbn13": "9781620100035", "year_first_published": "", "author": "Bryan Lee O'Malley", "num_pages": 216, "genres": ["Sequential Art > Graphic Novels", "Sequential Art > Comics", "Fiction", "Humor", "Graphic Novels Comics", "Sequential Art > Manga", "Young Adult", "Fantasy", "Romance", "Comics > Comic Book"], "num_ratings": "38869", "num_reviews": "1090", "average_rating": "4.29", "rating_distribution": {"5 Stars": 18901, "4 Stars": 13885, "3 Stars": 4942, "2 Stars": 754, "1 Star": 387}}