{"book_id_title": "8366402", "book_id": "8366402", "book_title": "The Tiger's Wife", "book_series": "", "book_series_uri": "", "isbn": "0385343841", "isbn13": "9780385343848", "year_first_published": "", "author": "T\u00e9a Obreht", "num_pages": 338, "genres": ["Fiction", "Historical > Historical Fiction", "Magical Realism", "Literary Fiction", "Book Club", "Fantasy", "Contemporary", "War", "Novels", "Adult Fiction"], "num_ratings": "100182", "num_reviews": "11014", "average_rating": "3.42", "rating_distribution": {"5 Stars": 17187, "4 Stars": 32336, "3 Stars": 31305, "2 Stars": 13719, "1 Star": 5635}}