{"book_id_title": "9397967", "book_id": "9397967", "book_title": "Abandon", "book_series": "Abandon #1", "book_series_uri": "/series/57816-abandon", "isbn": "0330453858", "isbn13": "9780330453851", "year_first_published": "", "author": "Meg Cabot", "num_pages": 304, "genres": ["Young Adult", "Fantasy", "Fantasy > Mythology", "Romance", "Fantasy > Paranormal", "Fiction", "Fantasy > Supernatural", "Romance > Paranormal Romance", "Mythology > Greek Mythology", "Retellings"], "num_ratings": "40101", "num_reviews": "3953", "average_rating": "3.69", "rating_distribution": {"5 Stars": 11499, "4 Stars": 12317, "3 Stars": 10407, "2 Stars": 3944, "1 Star": 1934}}