{"book_id_title": "9833184", "book_id": "9833184", "book_title": "The Fiery Heart", "book_series": "Bloodlines #4", "book_series_uri": "/series/54340-bloodlines", "isbn": "0141350083", "isbn13": "9780141350080", "year_first_published": "2013", "author": "Richelle Mead", "num_pages": 420, "genres": ["Young Adult", "Paranormal > Vampires", "Fantasy", "Fantasy > Paranormal", "Romance", "Fantasy > Magic", "Fantasy > Urban Fantasy", "Fantasy > Supernatural", "Romance > Paranormal Romance", "Fiction"], "num_ratings": "75757", "num_reviews": "5360", "average_rating": "4.30", "rating_distribution": {"5 Stars": 39464, "4 Stars": 23998, "3 Stars": 8878, "2 Stars": 2144, "1 Star": 1273}}